.project
.pydevproject
CHANGES.txt
Contributors.txt
MANIFEST.in
README.txt
paster.ini
setup.cfg
setup.py
docs/conf.py
docs/index.rst
tests/__init__.py
tests/test_widget.py
tw/__init__.py
tw.epiclock.egg-info/PKG-INFO
tw.epiclock.egg-info/SOURCES.txt
tw.epiclock.egg-info/dependency_links.txt
tw.epiclock.egg-info/entry_points.txt
tw.epiclock.egg-info/namespace_packages.txt
tw.epiclock.egg-info/not-zip-safe
tw.epiclock.egg-info/paster_plugins.txt
tw.epiclock.egg-info/requires.txt
tw.epiclock.egg-info/top_level.txt
tw/epiclock/__init__.py
tw/epiclock/release.py
tw/epiclock/samples.py
tw/epiclock/widgets.py
tw/epiclock/static/jquery.dateformat.js
tw/epiclock/static/jquery.dateformat.min.js
tw/epiclock/static/jquery.epiclock.css
tw/epiclock/static/jquery.epiclock.js
tw/epiclock/static/jquery.epiclock.min.js